afcluster/__init__.py
afcluster/af_cluster.py
afcluster/search_eps.py
afcluster/utils.py
afcluster/visuals.py
afcluster-0.1.2.dist-info/licenses/LICENSE.md
afcluster-0.1.2.dist-info/METADATA
afcluster-0.1.2.dist-info/WHEEL
afcluster-0.1.2.dist-info/top_level.txt
afcluster-0.1.2.dist-info/RECORD
